[{"business_status":"OPERATIONAL","formatted_address":"olaf ryes plass 3, 0552 Oslo","geometry":{"location":{"lat":59.9222899,"lng":10.7574672},"viewport":{"northeast":{"lat":59.92360292989271,"lng":10.75899187989272},"southwest":{"lat":59.92090327010727,"lng":10.75629222010728}}},"icon":"https://maps.gstatic.com/mapfiles/place_api/icons/v1/png_71/restaurant-71.png","icon_background_color":"#FF9E67","icon_mask_base_uri":"https://maps.gstatic.com/mapfiles/place_api/icons/v2/restaurant_pinlet","name":"Løkka Deli","opening_hours":{"open_now":false},"photos":[{"height":3648,"html_attributions":["<a href=\"https://maps.google.com/maps/contrib/102013580175484841132\">Trond Sørbø</a>"],"photo_reference":"AeJbb3fobNpAGHplq7haCC3uWG9J35qL5Ya5f6Wg0Il8yifBBYD24xRMdjTkhOuWDREjn9VGAyiBkqWWXmtXLxvvH7KnwQxWqZMoZjk9MYzXoB48uWM3V1xTbUDFp7VuHRl2y0-I41NKO8ucrMRPI7log6kRKyPhWMK7So4ddXcA1FJE_H1x","width":2736}],"place_id":"ChIJF4eL1G9vQUYRGTPg4QFtWeQ","plus_code":{"compound_code":"WQC4+VX Oslo","global_code":"9FFGWQC4+VX"},"price_level":2,"rating":4.3,"reference":"ChIJF4eL1G9vQUYRGTPg4QFtWeQ","types":["restaurant","food","point_of_interest","establishment"],"user_ratings_total":125},{"business_status":"OPERATIONAL","formatted_address":"Storgata 14-18, 0184 Oslo","geometry":{"location":{"lat":59.9135574,"lng":10.7504672},"viewport":{"northeast":{"lat":59.91489042989271,"lng":10.75183237989272},"southwest":{"lat":59.91219077010727,"lng":10.74913272010728}}},"icon":"https://maps.gstatic.com/mapfiles/place_api/icons/v1/png_71/restaurant-71.png","icon_background_color":"#FF9E67","icon_mask_base_uri":"https://maps.gstatic.com/mapfiles/place_api/icons/v2/restaurant_pinlet","name":"Burger King Nygata","opening_hours":{"open_now":true},"photos":[{"height":2976,"html_attributions":["<a href=\"https://maps.google.com/maps/contrib/106399580631688642008\">Mazdamiata</a>"],"photo_reference":"AeJbb3eiN460eAm3PKr8D2jau7c2oeyrs3R1LvgFN2ba2bJQ78BvAT6Mfl0m0ezuOAAmlFHox43mwarGZz3lFG8wkwq2itm33wCJlFreB-dupHy55Lv7h-ddOVXdBDgnEPY7EwUmvptq9N1NmxD6iqDEhje8XqUUeMfcCEAFdHwgt6YzoMkj","width":3968}],"place_id":"ChIJxap6ImJuQUYRU2yvtRTRZ1M","plus_code":{"compound_code":"WQ72+96 Oslo","global_code":"9FFGWQ72+96"},"price_level":1,"rating":3.5,"reference":"ChIJxap6ImJuQUYRU2yvtRTRZ1M","types":["restaurant","food","point_of_interest","establishment"],"user_ratings_total":578}]